[
  {
    "id": "idea-2026-03-05-rec-audit",
    "title": "Reverse Engineering Recommendation Algorithms",
    "description": "Создать систему, которая через обратное моделирование рекомендаций (inverse modeling) реконструирует алгоритмический профиль пользователя. По рекомендациям платформ (YouTube, TikTok, Netflix, LinkedIn) восстанавливается скрытый user embedding — приближённое представление того, как алгоритм \"видит\" пользователя. Это позволяет аудитировать рекомендательные системы на предмет bias, манипуляций и информационных пузырей. Pipeline: сбор рекомендаций → кодирование контента в embeddings → восстановление user vector (argmax similarity) → интерпретация в topics/interests/clusters. Актуально в контексте EU Digital Services Act и AI Act. По сути — nmap для рекомендательных систем.",
    "status": "idea",
    "results": null,
    "repoLink": null,
    "tags": [
      "algorithmic-transparency",
      "inverse-modeling",
      "embeddings",
      "recommendation-systems",
      "AI-governance"
    ],
    "createdAt": "2026-03-05T10:00:00Z",
    "updatedAt": "2026-03-05T10:00:00Z",
    "embedding": [
      0.066556,
      0.035372,
      0.053663,
      0.052826,
      0.029656,
      0.00118,
      -0.060558,
      -0.01369,
      -0.015092,
      0.084364,
      -0.079661,
      0.023588,
      -0.043373,
      0.07982,
      -0.026176,
      0.015535,
      -0.040782,
      0.007525,
      -0.026497,
      -0.012527,
      -0.025551,
      0.068122,
      0.082403,
      0.058654,
      -0.011468,
      0.075144,
      0.067519,
      -0.006601,
      0.007921,
      -0.05446,
      0.079482,
      -0.045435,
      -0.03508,
      -0.04081,
      0.050316,
      -0.028271,
      0.010069,
      -0.073304,
      0.081328,
      -0.067483,
      0.020223,
      0.025263,
      -0.047982,
      -0.067345,
      0.053798,
      -0.070145,
      0.036069,
      0.05098,
      -0.030555,
      -0.07307,
      -0.035371,
      -0.024703,
      -0.020337,
      -0.003759,
      0.011154,
      -0.039239,
      -0.039385,
      -0.076237,
      0.069982,
      -0.068817,
      0.070112,
      -0.035835,
      -0.06116,
      0.059307,
      0.04206,
      0.064598,
      -0.018443,
      0.064874,
      0.005227,
      -0.082113,
      -0.047733,
      0.076812,
      0.079105,
      -0.06052,
      -0.041869,
      -0.030822,
      -0.079611,
      0.024122,
      -0.052282,
      0.007776,
      0.06607,
      0.02106,
      -0.080074,
      -0.005033,
      -0.052152,
      0.081888,
      -0.055728,
      0.051183,
      0.056107,
      -0.029295,
      -0.011368,
      -0.081087,
      0.00728,
      -0.040107,
      -0.074996,
      0.031787,
      -0.004159,
      -0.059093,
      0.000796,
      -0.001279,
      -0.071785,
      0.027856,
      -0.023832,
      0.07269,
      0.05747,
      -0.073628,
      0.056454,
      -0.016914,
      0.057407,
      -0.056711,
      -0.071961,
      0.039249,
      0.024955,
      0.085796,
      0.080687,
      -0.055868,
      -0.018403,
      0.079756,
      -0.079263,
      0.067813,
      0.003398,
      -0.083221,
      0.06894,
      -0.010808,
      -0.07185,
      -0.063843,
      -0.051017,
      0.031877,
      0.021077,
      -0.03541,
      0.022867,
      -0.078644,
      0.000534,
      -0.071945,
      -0.046777,
      -0.048736,
      0.055083,
      0.055952,
      -0.042147,
      0.059746,
      0.006485,
      -0.041732,
      0.058823,
      -0.071969,
      0.002228,
      0.045082,
      -0.048733,
      -0.018276,
      0.045922,
      0.005495,
      -0.044514,
      0.010132,
      0.006559,
      -0.027418,
      -0.048003,
      0.024638,
      -0.018227,
      -0.074499,
      -0.026836,
      0.019416,
      -0.002505,
      -0.05893,
      -0.00028,
      0.066897,
      0.049092,
      -0.01105,
      0.080769,
      0.051286,
      -0.083922,
      -0.026837,
      -0.009071,
      -0.085739,
      -0.023406,
      -0.057739,
      0.006988,
      0.026646,
      0.007247,
      -0.076524,
      0.082567,
      0.030635,
      0.074128,
      -0.045405,
      -0.000648,
      -0.052181,
      -0.013147,
      -0.076877,
      -0.066552,
      -0.060549,
      0.044737,
      0.062275,
      -0.05863,
      0.076117,
      0.040157,
      -0.069848,
      -0.068673,
      0.032008,
      0.044239,
      -0.01718,
      0.028875,
      0.049727,
      -0.043065,
      0.074467,
      0.058379,
      -0.042692,
      -0.084116,
      -0.062041,
      -0.062632,
      0.055897,
      -0.007682,
      0.07962,
      0.068384,
      0.061073,
      -0.08286,
      0.015103,
      -0.04544,
      -0.038776,
      -0.03432,
      -0.067797,
      0.077782,
      -0.085748,
      -0.004441,
      0.007135,
      -0.079782,
      -0.082078,
      0.019354,
      -0.053524,
      -0.055761,
      -0.040581,
      -0.024082,
      0.079253,
      0.077563,
      0.037256,
      -0.057168,
      0.059879,
      0.07531,
      -0.06517,
      -0.034278,
      -0.02404,
      -0.024804,
      -0.05028,
      0.032156,
      -0.074443,
      -0.056516,
      -0.009982,
      0.016952,
      0.021016,
      -0.048037,
      -0.020709,
      0.004158,
      0.076385,
      0.012368,
      -0.034978,
      0.056871,
      -0.054685,
      -0.028765,
      0.004985,
      -0.067654,
      0.081393,
      0.031435,
      0.042884,
      0.013224,
      -0.071728,
      0.002542,
      0.045608,
      -0.007285,
      0.05854,
      0.01717,
      -0.016793,
      -0.0602,
      -0.021027,
      -0.041529,
      0.065325,
      -0.008769,
      -0.080016,
      0.02522,
      0.017715,
      0.061432,
      -0.056287,
      0.002664,
      -0.057561,
      0.019351,
      0.022049,
      0.043913,
      -0.063375,
      0.059644,
      0.039746,
      0.053795,
      -0.067125,
      -0.045199,
      0.068389,
      -0.054086,
      0.003158,
      0.025165,
      0.064267,
      -0.08529,
      0.009098,
      0.036203,
      -0.021041,
      0.007902,
      0.020233,
      -0.052205,
      0.065068,
      -0.034526,
      0.045058,
      0.082866,
      0.061118,
      0.047438,
      -0.06678,
      0.081419,
      0.076273,
      -0.015231,
      -0.060596,
      -0.046113,
      -0.031882,
      0.028362,
      -0.047951,
      -0.084113,
      -0.031234,
      -0.006279,
      0.011473,
      0.047242,
      0.014521,
      0.027433,
      0.005709,
      0.044422,
      0.083824,
      -0.049939,
      -0.01481,
      0.075385,
      -0.080065,
      0.082436,
      -0.009567,
      0.037852,
      0.084376,
      0.050785,
      0.072402,
      0.031443,
      -0.053639,
      -0.005133,
      -0.007389,
      0.002575,
      -0.032182,
      -0.016475,
      0.04609,
      0.022553,
      0.008125,
      0.010128,
      0.073119,
      0.012068,
      9.4e-05,
      0.051092,
      0.055129,
      0.055057,
      0.015899,
      -0.071115,
      -0.043923,
      0.031894,
      -0.08459,
      0.076001,
      0.052562,
      -0.045377,
      -0.072649,
      0.001061,
      0.015417,
      -0.047568,
      0.043536,
      0.081524,
      0.047378,
      -0.011921,
      -0.07286,
      -0.042463,
      -0.027656,
      -0.022294,
      -0.062693,
      0.065261,
      0.07387,
      -0.046736,
      0.082483,
      -0.032537,
      -0.031799,
      0.014143,
      0.010248,
      -0.039452,
      0.079845
    ]
  },
  {
    "id": "idea-2026-03-05-kan-ambient",
    "title": "KAN Models for City Ambient Sound Analysis",
    "description": "Применить Kolmogorov-Arnold Networks (KAN) к датасету городских эмбиентов для интерпретируемой классификации и извлечения математических формул. Pipeline: городские записи → акустические фичи (CLAP embeddings + acoustic indices через librosa/essentia) → KAN классификатор (город, сезон, время суток) → символьная регрессия (PySR + KAN built-in) → извлечение формул → использование параметров как conditioning inputs для AudioLDM2 генерации. Побочный продукт — интерпретируемый акустический fingerprint города/сезона/времени для урбанистов, звуковых дизайнеров и экологов. Первая публикация в нише KAN+audio, целевые конференции: DCASE workshop, ICASSP, EUSIPCO.",
    "status": "idea",
    "results": null,
    "repoLink": null,
    "tags": [
      "KAN",
      "audio",
      "urban-acoustics",
      "interpretable-ML",
      "audio-generation",
      "research"
    ],
    "createdAt": "2026-03-05T10:00:00Z",
    "updatedAt": "2026-03-05T10:00:00Z",
    "embedding": [
      0.061539,
      0.061306,
      0.022088,
      0.084094,
      -0.010796,
      0.037612,
      0.031247,
      0.085752,
      0.076821,
      -0.043283,
      -0.012012,
      0.014546,
      0.008644,
      0.022324,
      -0.01168,
      0.018638,
      0.068978,
      -0.073917,
      -0.026174,
      0.039714,
      0.007145,
      0.005514,
      -0.005286,
      0.006441,
      0.028263,
      -0.007235,
      0.078677,
      -0.04994,
      -0.066287,
      -0.046503,
      -0.001783,
      -0.053943,
      -0.005445,
      -0.064282,
      0.027199,
      0.071373,
      0.066418,
      -0.039774,
      -0.081274,
      0.077973,
      -0.019833,
      0.025032,
      0.054244,
      -0.044105,
      -0.020799,
      -0.00668,
      0.031479,
      -0.079889,
      0.047686,
      0.064501,
      -0.077476,
      0.017852,
      -0.070298,
      0.084284,
      -0.06439,
      0.073992,
      -0.003298,
      -0.054946,
      -0.036333,
      -0.022604,
      0.046698,
      -0.021103,
      -0.078589,
      -0.08263,
      -0.030353,
      -0.056567,
      0.055556,
      0.022918,
      -0.043292,
      0.085252,
      0.033043,
      0.002427,
      0.050022,
      0.076827,
      0.077504,
      0.014647,
      0.029344,
      0.027591,
      0.071695,
      0.085222,
      -0.013665,
      0.047716,
      -0.057195,
      0.080381,
      0.058935,
      0.037398,
      -0.085606,
      0.026459,
      0.048818,
      -0.015082,
      0.085426,
      -0.014386,
      0.037805,
      -0.059478,
      -0.05904,
      0.079686,
      0.047772,
      0.032496,
      0.01343,
      -0.079152,
      0.056421,
      0.019382,
      -0.016676,
      -0.068295,
      0.051157,
      -0.054856,
      0.082306,
      -0.066096,
      0.056042,
      -0.061878,
      0.009202,
      0.006506,
      0.001067,
      0.057487,
      -0.049753,
      -0.045874,
      0.058736,
      -0.046289,
      -0.060692,
      0.059062,
      -0.055396,
      0.047638,
      0.033853,
      0.050622,
      -0.080809,
      -0.063167,
      0.049274,
      0.016828,
      0.045552,
      -0.040744,
      -0.024346,
      0.039384,
      0.083069,
      0.06843,
      0.066834,
      0.045398,
      0.067767,
      0.006717,
      0.057527,
      0.016753,
      0.018778,
      0.039121,
      -0.037197,
      -0.051124,
      0.044644,
      -0.073858,
      0.070117,
      0.035461,
      0.074095,
      0.058425,
      0.069062,
      -0.085877,
      -0.02124,
      0.065593,
      0.047353,
      0.050512,
      0.012842,
      0.043813,
      0.068329,
      0.006889,
      -0.006314,
      0.047433,
      0.083548,
      0.029304,
      0.063599,
      0.049359,
      -0.085803,
      0.047316,
      -0.038353,
      0.058471,
      -0.005004,
      -0.045999,
      -0.076249,
      0.063001,
      0.008398,
      0.010671,
      0.032517,
      0.020717,
      -0.067124,
      0.001794,
      -0.053468,
      0.048806,
      -0.017373,
      0.055281,
      0.086272,
      -0.047707,
      0.038087,
      -0.038754,
      0.028456,
      -0.061252,
      0.050857,
      0.00197,
      -0.076959,
      -0.081304,
      -0.000622,
      -0.042498,
      -0.060595,
      -0.03671,
      -0.055481,
      -0.062201,
      -0.070248,
      -0.007711,
      -0.03419,
      0.048814,
      -0.08495,
      0.026857,
      0.0428,
      0.03033,
      0.028019,
      -0.007214,
      0.044519,
      -0.04746,
      -0.074935,
      -0.077963,
      0.080994,
      0.047464,
      0.054301,
      -0.084162,
      0.058291,
      -0.058601,
      -0.038378,
      0.047206,
      -0.052429,
      0.061447,
      -0.010222,
      -0.057618,
      -0.054361,
      -0.019316,
      -0.037584,
      0.084312,
      0.068506,
      -0.070312,
      -0.075924,
      0.044421,
      -0.015208,
      0.002121,
      0.074027,
      -0.057663,
      0.058613,
      0.020879,
      -0.050786,
      -0.042779,
      -0.066939,
      -0.077432,
      0.078693,
      -0.065832,
      0.04656,
      0.030324,
      0.002471,
      0.013001,
      0.026655,
      -0.057606,
      -0.079221,
      -0.049771,
      0.012138,
      0.022495,
      0.029531,
      0.021107,
      -0.015124,
      0.019258,
      0.060726,
      0.025966,
      -0.082214,
      -0.030693,
      0.065618,
      0.071051,
      0.050153,
      0.036984,
      0.024438,
      0.037136,
      0.057686,
      -0.078559,
      -0.060282,
      -0.069593,
      -0.016787,
      0.001249,
      -0.06251,
      0.005604,
      -0.0065,
      -0.041661,
      -0.016273,
      0.054086,
      0.085041,
      -0.067399,
      0.025987,
      -0.0065,
      -0.06602,
      0.067929,
      0.074397,
      0.045244,
      0.027581,
      -0.080051,
      0.080067,
      -0.059333,
      0.02969,
      0.00657,
      0.059637,
      0.037147,
      0.008804,
      -0.05844,
      0.073537,
      0.01588,
      -0.024718,
      0.012768,
      0.070497,
      0.045757,
      -0.007294,
      0.058004,
      -0.022035,
      -0.018086,
      -0.086065,
      0.051387,
      -0.040165,
      -0.013337,
      -0.010448,
      0.079776,
      -0.082769,
      0.021243,
      -0.011859,
      0.035446,
      0.038562,
      -0.011146,
      -0.074756,
      -0.053072,
      0.009039,
      0.058595,
      -0.001715,
      -0.084267,
      -0.051898,
      0.027734,
      -0.080973,
      -0.049734,
      0.008355,
      -0.016083,
      -0.07521,
      -6e-05,
      -0.086394,
      -0.083129,
      -0.060593,
      -0.073588,
      0.017755,
      0.000946,
      -0.007546,
      0.023003,
      0.005479,
      -0.01681,
      0.043104,
      -0.005349,
      0.067471,
      0.011275,
      0.064686,
      0.041052,
      0.06581,
      0.007224,
      -0.075976,
      0.080844,
      -0.001177,
      -0.044525,
      0.053886,
      0.07976,
      0.030731,
      0.035874,
      -0.077057,
      0.004573,
      -0.003741,
      0.039687,
      0.042654,
      0.041914,
      0.006956,
      -0.033847,
      -0.02761,
      0.084265,
      -0.03539,
      -0.058657,
      0.032975,
      0.086376,
      0.0163,
      -0.028524,
      0.037867,
      0.009241,
      -0.0147,
      0.056223,
      -0.010765,
      0.003629
    ]
  },
  {
    "id": "idea-2026-03-07-perspective-routing",
    "title": "Perspective-Aware Routing in Latent Space",
    "description": "Опорный вектор определяет \"позицию наблюдателя\" в латентном пространстве, которое разбито на выученные сектора-перспективы — и на основе этого условно активирует разные пути через сеть. Три компонента: (1) Anchor Vector — живёт в пространстве эмбеддингов, представляет не *что*, а *откуда смотрим*, обучается вместе с моделью; (2) Perspective Sectors — латентное пространство делится на N выученных секторов, каждый = своя перспектива на смысл; (3) Perspective-Conditioned Activation — сектор определяет путь через сеть, разные перспективы = разные веса/слои. Отличие от MoE: роутинг по геометрии пространства, а не по содержанию. Отличие от Gradient Routing: семантика перспективная, а не отсутствует. Стек: sentence-transformers, umap-learn, PyTorch, датасет AG News / 20newsgroups.",
    "status": "killed",
    "results": "Шаг 1 (геометрический эксперимент) выполнен. На статических эмбеддингах (GloVe) V=x−A действительно разделяет полисемию (Silhouette 0.21 vs −0.002 у абсолютных x). Однако на контекстных эмбеддингах (BERT) V=x−A ухудшает разделение (0.20 vs 0.24 у абсолютных). Вывод: PAR решает проблему, которую attention-механизм уже решил — контекстуализацию. В современных моделях с контекстными эмбеддингами практический смысл минимален. Cosine(x−A, S) как роутер не даёт принципиального преимущества перед стандартным линейным MoE-роутером W·x, т.к. обучаемый anchor A сводится к learnable bias. Идея закрыта на этапе PoC.",
    "repoLink": null,
    "tags": [
      "latent-space",
      "routing",
      "perspective-geometry",
      "neural-architecture",
      "embeddings",
      "research"
    ],
    "createdAt": "2026-03-07T10:00:00Z",
    "updatedAt": "2026-03-11T12:00:00Z",
    "embedding": [
      0.073925,
      -0.03759,
      0.071496,
      0.027463,
      0.069144,
      -0.076583,
      0.042246,
      0.07614,
      0.084316,
      -0.08512,
      -0.00793,
      -0.034497,
      0.068938,
      0.0791,
      -0.049925,
      -0.084967,
      -0.062983,
      0.05071,
      0.017683,
      0.058786,
      0.031014,
      0.0476,
      0.085435,
      -0.081714,
      0.003851,
      -0.028947,
      0.072641,
      0.022532,
      -0.066809,
      -0.083774,
      -0.049135,
      0.073249,
      0.06492,
      -0.023399,
      -0.053724,
      0.045356,
      -0.043349,
      0.017548,
      0.01353,
      0.068544,
      -0.029727,
      -0.067956,
      -0.066059,
      0.080926,
      0.059259,
      -0.080016,
      -0.079161,
      -0.066455,
      0.043951,
      0.04359,
      0.059993,
      0.036689,
      -0.006921,
      -0.042718,
      -0.083328,
      -0.080486,
      0.051442,
      0.06965,
      0.048165,
      0.024409,
      -0.038226,
      -0.025886,
      -0.070062,
      0.046368,
      -0.07666,
      0.047485,
      0.033287,
      0.041818,
      -0.068933,
      -0.085232,
      0.052093,
      -0.036743,
      0.024278,
      0.031245,
      0.009214,
      -0.05391,
      0.05854,
      -0.06741,
      -0.039135,
      0.052576,
      -0.047073,
      0.049215,
      -0.061979,
      -0.015559,
      0.08527,
      0.042457,
      -0.016553,
      -0.033211,
      -0.010062,
      0.007713,
      -0.053115,
      -0.057749,
      0.057833,
      0.004014,
      0.051528,
      0.065825,
      0.036983,
      -0.022937,
      -0.004861,
      -0.063631,
      -0.012298,
      -0.044356,
      0.027507,
      -0.041804,
      -0.047317,
      0.026566,
      -0.014844,
      -0.000298,
      0.01448,
      -0.004693,
      -0.062847,
      0.053637,
      0.050993,
      0.021519,
      -0.003838,
      0.008756,
      0.014511,
      -0.080703,
      -0.078555,
      -0.004037,
      -0.021708,
      -0.024231,
      0.034245,
      -0.013516,
      -0.027621,
      0.085207,
      -0.068556,
      0.025119,
      0.084003,
      -0.047806,
      0.07025,
      -0.077362,
      -0.06903,
      -0.030826,
      0.076446,
      -0.000903,
      0.005931,
      -0.042261,
      0.023321,
      0.02487,
      -0.008797,
      -0.017432,
      -0.069713,
      -0.041212,
      0.062568,
      0.042511,
      0.027631,
      -0.035933,
      0.017779,
      -0.061847,
      -0.013944,
      0.041415,
      0.018785,
      0.066273,
      0.064359,
      -0.002601,
      -0.07624,
      -0.04653,
      -0.023843,
      -0.018194,
      -0.069152,
      -0.037292,
      -0.016711,
      0.077156,
      -0.080423,
      -0.014971,
      0.068238,
      0.075096,
      -0.079285,
      0.065328,
      -0.043182,
      0.023445,
      -0.062676,
      -0.062008,
      -0.060665,
      -0.064198,
      -0.081085,
      0.053497,
      -0.071999,
      0.004623,
      0.029821,
      -0.027447,
      -0.004013,
      0.081099,
      0.085956,
      0.083956,
      -0.007264,
      0.077936,
      -0.072791,
      0.08324,
      0.029209,
      0.02213,
      -0.035857,
      -0.073546,
      0.032836,
      0.039754,
      0.031416,
      0.078187,
      -0.066502,
      0.040001,
      0.033697,
      -0.000722,
      -0.008789,
      -0.048793,
      -0.022742,
      -0.017783,
      0.050425,
      0.0118,
      -0.072459,
      -0.005373,
      0.078656,
      -0.016782,
      0.029382,
      0.078319,
      -0.042557,
      -0.051523,
      -0.027634,
      0.078465,
      -0.024569,
      -0.08256,
      0.082606,
      0.067063,
      0.062281,
      -0.012043,
      -0.043946,
      -0.079128,
      0.056388,
      0.073116,
      0.036457,
      0.043908,
      -0.050108,
      0.040728,
      -0.05229,
      -0.045658,
      -0.059624,
      -0.04277,
      -0.039293,
      0.084101,
      0.005951,
      -0.019578,
      -0.041522,
      -0.008961,
      0.076738,
      0.013252,
      0.076046,
      0.063973,
      0.041828,
      0.051765,
      0.043296,
      -0.047069,
      -0.067213,
      -0.064841,
      -0.021896,
      0.0337,
      -0.025949,
      -0.030892,
      0.076918,
      0.072854,
      -0.078086,
      -0.013384,
      -0.040582,
      -0.025609,
      0.01875,
      -0.033984,
      0.049474,
      -0.067362,
      -0.087008,
      -0.029273,
      0.080289,
      -0.030453,
      -0.041292,
      0.083402,
      -0.035045,
      0.007919,
      0.059349,
      -0.022002,
      0.018719,
      0.032139,
      -0.033884,
      -0.057178,
      -0.053733,
      -0.075597,
      -0.059096,
      -0.023785,
      0.066904,
      0.022466,
      0.007475,
      0.067944,
      0.002469,
      0.005758,
      0.014741,
      -0.003001,
      -0.00642,
      0.078277,
      0.080156,
      0.014981,
      -0.011549,
      -0.031885,
      0.051598,
      -0.078349,
      -0.041501,
      -0.008863,
      0.017304,
      0.035203,
      0.054229,
      0.000978,
      -0.028045,
      0.084268,
      0.014404,
      0.007876,
      0.064436,
      -0.02284,
      0.009688,
      0.019337,
      0.064732,
      -0.021979,
      0.001175,
      -0.011731,
      0.081367,
      0.034296,
      0.026405,
      -0.012299,
      0.037212,
      -0.048539,
      0.024632,
      0.016373,
      -0.080598,
      0.079363,
      -0.048828,
      -0.036912,
      -0.084498,
      -0.045226,
      0.050643,
      0.018239,
      0.017018,
      -0.034351,
      0.025727,
      -0.018847,
      -0.079093,
      0.018906,
      0.031144,
      -0.024088,
      -0.087213,
      0.059672,
      0.018344,
      -0.073438,
      0.000683,
      0.071926,
      -0.044384,
      -0.010354,
      0.074701,
      0.085489,
      -0.010426,
      0.002719,
      -0.054265,
      0.046733,
      0.068289,
      0.068308,
      -0.083738,
      0.026149,
      -0.04675,
      0.026739,
      -0.079176,
      0.030618,
      0.06006,
      0.060595,
      0.026144,
      -0.06053,
      0.079418,
      0.049225,
      0.03187,
      -0.038309,
      -0.033948,
      -0.064547,
      0.075449,
      0.021591,
      0.046153,
      -0.012438,
      0.059289,
      -0.013173,
      -0.005423,
      -0.010615,
      0.016583,
      0.028629
    ]
  },
  {
    "id": "idea-2026-03-11-embedding-topology",
    "title": "Embedding Topology — Blind Spots in Knowledge",
    "description": "Исследование топологии embedding space для обнаружения пробелов в знаниях модели/датасета. Области низкой плотности (\"дыры\") в пространстве эмбеддингов = то, чего модель не знает. Метод: найти зоны низкой плотности, взять N ближайших соседей вокруг дыры, проанализировать их семантику — если соседи из разных доменов, это неисследованный стык между темами; если из одного домена с низкой плотностью — пробел внутри темы. Практическая польза: инструмент аудита датасетов и моделей, визуализация \"слепых пятен\". Стек: sentence-transformers, UMAP, HDBSCAN, scipy spatial.",
    "embedding": [
      0.004691,
      -0.054621,
      0.068677,
      0.06089,
      0.086265,
      -0.016512,
      -0.08363,
      -0.007386,
      0.082189,
      -0.062768,
      0.054891,
      0.039915,
      0.054788,
      -0.001658,
      0.077782,
      0.063879,
      0.010279,
      0.063756,
      -0.012452,
      0.053982,
      -0.062968,
      0.048932,
      0.030059,
      0.034552,
      0.048523,
      -0.081618,
      -0.051213,
      0.000749,
      0.074066,
      0.036327,
      -0.065279,
      -0.077885,
      0.003518,
      -0.079877,
      0.072749,
      -0.061405,
      0.086147,
      -0.002975,
      0.038905,
      -0.08199,
      0.056534,
      -0.072165,
      0.020753,
      0.064211,
      0.080572,
      0.009936,
      -0.077601,
      0.006749,
      -0.081776,
      -0.081508,
      0.085942,
      -0.026769,
      0.012787,
      0.081644,
      0.06942,
      0.084726,
      -0.039568,
      -0.051516,
      -0.070239,
      -0.015144,
      -0.018271,
      0.009932,
      0.029333,
      0.057312,
      -0.020174,
      -0.080623,
      -0.009224,
      0.011404,
      0.068917,
      -0.079166,
      -0.055033,
      -0.085783,
      -0.061371,
      0.017199,
      0.003886,
      -0.029564,
      0.068906,
      -0.085097,
      0.060382,
      -0.043065,
      0.075294,
      -0.08669,
      0.018068,
      0.001337,
      -0.019827,
      0.039374,
      -0.05382,
      -0.038395,
      0.037479,
      0.029289,
      -0.085,
      -0.035067,
      0.039734,
      0.064787,
      0.049553,
      0.058243,
      -0.007867,
      -0.000886,
      0.035735,
      -0.035757,
      -0.046095,
      -0.064866,
      0.007089,
      0.023963,
      0.062647,
      0.064399,
      -0.039374,
      -0.025547,
      -0.067666,
      0.022462,
      -0.022447,
      -0.055051,
      0.004994,
      0.014558,
      -0.038401,
      -0.027406,
      0.049113,
      -0.030733,
      -0.045889,
      -0.012352,
      -0.008085,
      0.017158,
      0.086252,
      0.045498,
      0.016688,
      -0.057489,
      0.010784,
      -0.02557,
      0.071798,
      0.03606,
      0.002372,
      -0.045414,
      0.067814,
      -0.046005,
      -0.08115,
      -0.019619,
      0.040355,
      -0.076922,
      -0.049492,
      0.06943,
      -0.009234,
      0.028061,
      0.045086,
      0.039322,
      0.072726,
      0.009342,
      0.023597,
      0.020034,
      -0.032155,
      -5.9e-05,
      0.055658,
      0.001903,
      0.030268,
      -0.063172,
      0.033217,
      -0.065442,
      -0.085245,
      -0.012373,
      -0.055273,
      0.067226,
      0.04921,
      0.075324,
      -0.037556,
      -0.082789,
      -0.071961,
      -0.027037,
      0.085373,
      0.076055,
      -0.022204,
      -0.037117,
      -0.037543,
      0.025841,
      -0.07138,
      0.056246,
      -0.044796,
      -0.001017,
      -0.078511,
      0.026962,
      0.066703,
      0.053992,
      0.065785,
      -0.006134,
      0.05575,
      0.055247,
      -0.015713,
      -0.01858,
      -0.029767,
      -0.013516,
      -0.030342,
      -0.06911,
      0.073183,
      -0.05924,
      0.075224,
      -0.01723,
      -0.082904,
      0.085635,
      -0.019225,
      0.069054,
      0.059016,
      -0.053653,
      -0.046144,
      0.026594,
      -0.085213,
      0.086705,
      0.011491,
      -0.034587,
      -0.06214,
      -0.031492,
      0.036182,
      0.017471,
      0.056756,
      -0.064079,
      0.036857,
      0.068799,
      -0.050576,
      0.06277,
      0.006184,
      -0.009002,
      0.041024,
      -0.014673,
      -0.044566,
      -0.067851,
      -0.06099,
      -0.067571,
      -0.074087,
      -0.033545,
      -0.029327,
      -0.050756,
      0.036725,
      0.05314,
      -0.070132,
      -0.040117,
      0.020263,
      -0.04844,
      0.002823,
      -0.075272,
      0.043291,
      0.043054,
      0.065488,
      -0.04332,
      0.005488,
      -0.074508,
      0.062797,
      -0.000179,
      -0.017651,
      0.076345,
      -0.07818,
      -0.022419,
      0.0472,
      -0.025994,
      -0.028917,
      0.013876,
      0.053489,
      0.058919,
      -0.029589,
      0.070026,
      0.045438,
      0.055191,
      -0.016899,
      -0.008592,
      -0.033665,
      -0.008626,
      -0.021876,
      0.001879,
      0.027774,
      -0.082679,
      0.003657,
      0.032785,
      0.06149,
      -0.037108,
      0.079197,
      0.010304,
      0.086177,
      0.03784,
      0.083256,
      0.009376,
      0.0633,
      -0.050414,
      0.000562,
      -0.035377,
      0.031422,
      -0.066542,
      -0.063276,
      -0.067774,
      -0.016455,
      -0.061248,
      -0.083358,
      0.071746,
      -0.018254,
      -0.075263,
      -0.082496,
      -0.048631,
      0.047424,
      0.031388,
      -0.021162,
      -0.004429,
      -0.026198,
      -0.075826,
      -0.028606,
      -0.01419,
      -0.010508,
      0.001557,
      0.084012,
      0.040394,
      -0.013572,
      -0.059348,
      0.045952,
      0.027007,
      -0.020936,
      0.0507,
      0.05576,
      0.053048,
      0.029588,
      0.040745,
      0.043651,
      0.073018,
      0.046503,
      -0.024079,
      0.064686,
      0.041425,
      -0.04913,
      -0.059334,
      0.014017,
      0.040916,
      -0.077688,
      0.054661,
      0.070983,
      0.076028,
      0.00241,
      -0.033015,
      0.063337,
      0.005098,
      -0.015737,
      -0.004282,
      0.027441,
      -0.004011,
      0.082506,
      0.08369,
      -0.018095,
      0.066249,
      0.010173,
      -0.045719,
      -0.026184,
      -0.037592,
      0.085276,
      -0.059605,
      -0.020665,
      0.024768,
      0.081581,
      -0.039073,
      0.022578,
      -0.05289,
      -0.032126,
      -0.058316,
      -0.079266,
      0.075333,
      -0.011688,
      0.024147,
      0.062205,
      0.068717,
      0.056695,
      0.035187,
      0.018557,
      -0.084562,
      -0.085107,
      0.037331,
      0.047099,
      0.037955,
      0.028276,
      0.042229,
      0.025335,
      -0.082056,
      -0.024525,
      0.011644,
      0.005051,
      -0.028291,
      0.041099,
      -0.033251,
      0.055881,
      0.022349,
      -0.012259,
      -0.060444,
      -0.063921,
      -0.03132
    ],
    "status": "idea",
    "results": null,
    "repoLink": null,
    "tags": [
      "embedding-topology",
      "knowledge-gaps",
      "density-analysis",
      "embeddings",
      "research"
    ],
    "createdAt": "2026-03-11T12:00:00Z",
    "updatedAt": "2026-03-11T12:00:00Z"
  },
  {
    "id": "idea-2026-03-11-semantic-pressure",
    "title": "Semantic Pressure — How Context Deforms Meaning",
    "description": "Исследование \"семантического давления\" контекста на значение слова. Одно и то же слово в разных контекстах получает разные контекстные эмбеддинги — направление и величина сдвига относительно статического эмбеддинга = вектор давления контекста. Гипотеза: по этому вектору можно определить тип влияния контекста (нейтральный, позитивный, негативный, манипулятивный). Практическая польза: детекция framing и манипулятивной подачи информации, анализ пропаганды. Стек: BERT, GloVe, sentence-transformers, визуализация векторных полей.",
    "embedding": [
      -0.071754,
      0.0551,
      0.03336,
      0.065984,
      0.037607,
      0.013473,
      -0.000346,
      0.036167,
      -0.044774,
      -0.00109,
      0.016667,
      -0.009482,
      -0.041051,
      -0.052086,
      0.037415,
      -0.055973,
      0.002514,
      0.000432,
      0.084427,
      -0.018705,
      0.003082,
      -0.011501,
      0.065518,
      0.049664,
      0.030386,
      0.021054,
      -0.011667,
      -0.051991,
      0.005498,
      -0.022443,
      -0.04562,
      0.00549,
      0.062567,
      -0.004491,
      -0.050414,
      -0.055322,
      0.090627,
      -0.053691,
      0.084767,
      0.059575,
      -0.027532,
      -0.015432,
      0.030371,
      0.021215,
      -0.053273,
      -0.016521,
      -0.064803,
      -0.013205,
      0.064832,
      -0.058616,
      -0.062873,
      0.052269,
      -0.012941,
      0.081182,
      0.010144,
      -0.002819,
      0.089272,
      0.000547,
      -0.01713,
      0.088774,
      0.033887,
      -0.041916,
      0.018367,
      -0.014766,
      -0.041719,
      0.017157,
      -0.064037,
      -0.040473,
      0.070578,
      -0.049298,
      0.028406,
      0.029198,
      -0.012013,
      -0.007759,
      -0.063025,
      -0.059094,
      -0.028982,
      0.063869,
      0.055962,
      -0.041455,
      -0.065583,
      -0.070003,
      0.029248,
      -0.050627,
      0.02445,
      0.089334,
      0.083063,
      -0.01039,
      -0.083956,
      0.035945,
      -0.060559,
      -0.016071,
      0.073998,
      0.065265,
      -0.036382,
      0.065807,
      -0.049975,
      -0.016713,
      0.017124,
      0.000406,
      -0.003942,
      -0.014227,
      -0.057437,
      0.084192,
      -0.079755,
      -0.025343,
      0.060818,
      -0.055147,
      0.066044,
      0.033152,
      -0.029475,
      -0.08253,
      -0.022843,
      -0.03697,
      0.030327,
      -0.054009,
      -0.062164,
      0.06014,
      -0.004289,
      -0.041274,
      -0.085062,
      -0.059222,
      -0.08181,
      -0.060475,
      0.054945,
      -0.041486,
      -0.039641,
      0.007117,
      0.071313,
      0.024177,
      0.052939,
      -0.003038,
      0.039069,
      0.004958,
      0.047176,
      -0.051046,
      -0.06799,
      -0.030232,
      0.016039,
      0.086276,
      0.055809,
      -0.088477,
      0.084899,
      0.052438,
      0.076,
      -0.059344,
      -0.009436,
      -0.008346,
      0.066828,
      0.035101,
      -0.068903,
      -0.033016,
      0.007254,
      -0.022582,
      -0.003693,
      -0.062237,
      0.059244,
      0.01881,
      -0.076855,
      0.063371,
      0.054531,
      -0.008295,
      -0.07968,
      -0.08139,
      -0.020418,
      -0.043987,
      -0.057109,
      0.023994,
      0.066738,
      -0.081063,
      -0.020743,
      -0.087267,
      -0.08228,
      0.07712,
      0.003992,
      -0.04425,
      -0.005416,
      0.030083,
      -0.022793,
      0.075665,
      -0.00462,
      0.050038,
      -0.001629,
      0.025701,
      -0.005019,
      -0.051968,
      0.086215,
      0.000615,
      -0.040809,
      0.076016,
      0.056292,
      0.074018,
      0.058189,
      0.004785,
      0.058661,
      -0.043649,
      -0.067217,
      -0.037175,
      0.06555,
      -0.06856,
      0.066759,
      0.030564,
      -0.037678,
      -0.07939,
      -0.035602,
      -0.006658,
      -0.013906,
      0.077629,
      -0.077335,
      -0.061691,
      0.074549,
      0.045286,
      0.006287,
      -0.04672,
      0.051009,
      -0.086748,
      -0.075586,
      -0.078181,
      -0.064428,
      0.008014,
      -0.037702,
      -0.045689,
      -0.05518,
      0.009187,
      -0.060332,
      0.085744,
      0.015342,
      -0.022668,
      -0.014551,
      -0.038215,
      0.049887,
      -0.030468,
      -0.081287,
      0.052839,
      -0.005869,
      -0.081182,
      -0.065379,
      0.026963,
      0.033824,
      0.089917,
      -0.069314,
      0.002989,
      0.020302,
      -0.030638,
      -0.009691,
      -0.048906,
      0.050439,
      0.084119,
      0.086159,
      0.053204,
      0.036324,
      0.061472,
      0.065858,
      0.01763,
      0.008946,
      -0.030318,
      -0.017529,
      -0.021489,
      0.082033,
      0.070285,
      0.014138,
      0.065416,
      0.002211,
      0.021753,
      0.035359,
      0.000986,
      -0.061185,
      -0.062148,
      0.084197,
      -0.006358,
      0.075939,
      -0.023054,
      -0.030223,
      -0.080242,
      -0.067151,
      -0.04349,
      -0.008387,
      0.062257,
      0.066037,
      0.032596,
      -0.075739,
      0.036401,
      -0.011593,
      -0.061347,
      0.056945,
      0.07879,
      0.049592,
      0.005172,
      -0.012834,
      0.057672,
      0.022014,
      8.8e-05,
      0.048812,
      0.016936,
      -0.045031,
      -0.079549,
      -0.017102,
      -0.024545,
      0.041169,
      0.047978,
      -0.086724,
      0.066978,
      -0.032662,
      0.035535,
      0.053565,
      0.01491,
      -0.052384,
      -0.026695,
      0.025956,
      -0.06376,
      -0.088489,
      -0.070913,
      0.036133,
      0.01447,
      -0.045766,
      0.002425,
      0.057844,
      -0.055072,
      -0.02437,
      -0.067619,
      -0.001371,
      0.055792,
      -0.020764,
      -0.064985,
      -0.090786,
      -0.082496,
      0.048558,
      -0.007727,
      -0.064538,
      -0.019893,
      0.017603,
      -0.004392,
      -0.015529,
      0.051267,
      0.034491,
      -0.034064,
      0.076362,
      -0.027285,
      0.035263,
      0.026096,
      0.080688,
      -0.055921,
      0.053949,
      0.074672,
      -0.009184,
      0.033886,
      -0.068547,
      -0.071818,
      -0.019374,
      -0.037069,
      -0.014305,
      0.062332,
      -0.057579,
      -0.027528,
      -0.06712,
      0.083109,
      -0.067889,
      0.04441,
      -0.014107,
      -0.0327,
      -0.05213,
      -0.077783,
      -0.034809,
      -0.069448,
      -0.077072,
      -0.073067,
      -0.015428,
      -0.037302,
      -0.00502,
      -0.073709,
      0.001683,
      -0.020811,
      -0.067061,
      0.087505,
      -0.022476,
      -0.007948,
      -0.034718,
      0.044536,
      -0.065243,
      -0.023477,
      0.072572,
      -0.071426,
      0.022749,
      -0.07233
    ],
    "status": "idea",
    "results": null,
    "repoLink": null,
    "tags": [
      "semantic-pressure",
      "context-analysis",
      "framing-detection",
      "embeddings",
      "research"
    ],
    "createdAt": "2026-03-11T12:00:00Z",
    "updatedAt": "2026-03-11T12:00:00Z"
  },
  {
    "id": "idea-2026-03-11-embedding-erosion",
    "title": "Embedding Erosion — Semantic Drift Over Time",
    "description": "Исследование дрейфа семантики слов и концепций во времени через сравнение эмбеддингов моделей, обученных на данных разных периодов. Как изменился вектор \"twitter\" после ребрендинга в X? Как сдвинулся \"corona\" после пандемии? Метод: сравнение эмбеддингов из моделей разных эпох, построение карты семантического дрейфа, выявление слов с максимальным сдвигом. Практическая польза: детекция устаревших моделей, определение когда пора дообучать, исторический анализ языка. Стек: Word2Vec/GloVe разных годов, temporal word embeddings, UMAP.",
    "embedding": [
      0.044325,
      0.022832,
      0.058453,
      -0.066969,
      0.038726,
      0.027718,
      0.023491,
      0.016244,
      -0.061696,
      0.055611,
      -0.019059,
      0.013897,
      0.024707,
      -0.072362,
      0.080932,
      0.014585,
      0.022702,
      0.022585,
      0.047602,
      -0.033505,
      -0.032746,
      -0.035486,
      -0.04188,
      -0.07011,
      -0.042488,
      0.070984,
      -0.07245,
      -0.038522,
      -0.061144,
      -0.024905,
      -0.029507,
      0.057951,
      0.048406,
      -0.002681,
      0.012476,
      -0.019814,
      0.069194,
      0.026465,
      -0.062492,
      0.077656,
      0.085977,
      -0.071844,
      -0.009112,
      -0.007556,
      0.022558,
      0.047608,
      0.039182,
      -0.003238,
      -0.019459,
      -0.059141,
      0.083228,
      -0.060337,
      -0.0753,
      -0.04147,
      0.006879,
      0.037647,
      -0.057361,
      0.008829,
      -0.081023,
      0.042437,
      -0.02995,
      -0.049188,
      -0.063425,
      -0.017768,
      0.036174,
      -0.074887,
      0.074638,
      0.048112,
      -0.079223,
      0.054273,
      -0.044421,
      0.052852,
      -0.030484,
      0.069709,
      0.042246,
      0.014315,
      0.055268,
      0.028127,
      -0.045857,
      0.040849,
      -0.010097,
      0.07844,
      0.070214,
      0.032452,
      -0.068344,
      -0.07723,
      0.074237,
      -0.028886,
      -0.060989,
      0.086199,
      -0.046094,
      -0.070421,
      -0.014706,
      -0.072328,
      0.051764,
      0.052737,
      -0.068976,
      0.044816,
      -0.03211,
      -0.012974,
      0.075955,
      0.024567,
      0.008201,
      -0.084238,
      0.057204,
      0.057703,
      -0.040628,
      0.079806,
      0.003644,
      -0.03485,
      -0.077385,
      0.076158,
      -0.017704,
      0.000595,
      0.064123,
      0.005841,
      -0.083749,
      -0.080611,
      0.033903,
      -0.082153,
      -0.009641,
      -0.01401,
      -0.070294,
      -0.033374,
      -0.083226,
      0.063826,
      -0.076592,
      -0.020258,
      0.018709,
      -0.059381,
      0.080402,
      -0.012134,
      0.081571,
      -0.024836,
      0.08536,
      0.067572,
      -0.031781,
      0.026627,
      0.058778,
      0.010739,
      0.024314,
      0.079022,
      -0.072176,
      -0.059941,
      0.078519,
      0.00271,
      -0.079591,
      -0.038469,
      0.082437,
      -0.038136,
      -0.007859,
      -0.026536,
      -0.016425,
      -0.051848,
      0.062837,
      -0.027303,
      -0.027501,
      -0.050448,
      0.083677,
      0.073845,
      0.082011,
      -0.07316,
      0.081045,
      0.063096,
      -0.066642,
      0.068269,
      0.063466,
      -0.047801,
      0.03023,
      -0.024236,
      -0.062327,
      -0.030341,
      0.030535,
      0.022218,
      0.012487,
      0.070245,
      0.069467,
      0.071897,
      -0.013318,
      -0.004184,
      0.044662,
      0.015,
      -0.058358,
      -0.031424,
      -0.005162,
      0.077431,
      0.023519,
      -0.065434,
      -0.055964,
      -0.008217,
      0.085836,
      0.034503,
      -0.080065,
      0.00952,
      -0.042224,
      0.046706,
      0.075937,
      0.071284,
      0.05149,
      -0.039987,
      0.067931,
      -0.057746,
      0.031552,
      -0.059364,
      0.03832,
      -0.082266,
      -0.067319,
      -0.052862,
      -0.064678,
      0.060062,
      0.064314,
      0.026514,
      0.039327,
      -0.005074,
      -0.065413,
      -0.012018,
      -0.05651,
      -0.00277,
      -0.025874,
      0.006666,
      0.071845,
      0.02958,
      0.061839,
      -0.011567,
      0.039973,
      0.059494,
      0.017643,
      -0.059655,
      0.018294,
      0.049067,
      0.044825,
      0.04331,
      -0.077759,
      0.001093,
      0.056605,
      0.075398,
      -0.006625,
      0.012959,
      0.023171,
      -0.002386,
      0.018625,
      0.030035,
      -0.072365,
      -0.033964,
      0.05946,
      -0.057839,
      0.08265,
      0.024542,
      -0.061839,
      0.061075,
      0.049995,
      -0.008111,
      0.006878,
      0.026395,
      0.030066,
      -0.029593,
      -0.072551,
      -0.014546,
      0.021455,
      0.086384,
      0.064434,
      0.017799,
      -0.074708,
      0.062446,
      -0.030496,
      -0.080993,
      0.048113,
      0.00107,
      -0.055836,
      -0.012593,
      -0.014048,
      0.03741,
      -0.014122,
      0.082502,
      0.016197,
      0.067516,
      0.027782,
      0.021616,
      0.037797,
      -0.020825,
      -0.06936,
      -0.031914,
      0.013286,
      0.033852,
      0.022044,
      0.07007,
      0.068388,
      -0.076741,
      -0.050758,
      0.080083,
      0.049112,
      -0.043544,
      -0.071141,
      -0.055012,
      -0.019666,
      -0.041098,
      0.083087,
      0.019776,
      0.014316,
      0.031627,
      0.041907,
      -0.008882,
      -0.07136,
      -0.036611,
      0.039004,
      0.009879,
      0.050246,
      0.059484,
      -0.030228,
      0.003397,
      0.030685,
      0.006989,
      0.06201,
      -0.025559,
      -0.05475,
      -0.07537,
      -0.026188,
      0.026707,
      -0.031964,
      0.04401,
      -0.030744,
      -0.018343,
      -0.019595,
      0.055182,
      -0.051977,
      -0.077466,
      0.037687,
      -0.071651,
      -0.020479,
      -0.027225,
      -0.063589,
      -0.043558,
      0.021387,
      -0.047612,
      0.018343,
      -0.073398,
      0.050021,
      -0.011432,
      0.069119,
      0.01119,
      0.013665,
      -0.044935,
      0.005328,
      -0.001915,
      -0.029622,
      0.028041,
      0.073164,
      -0.029911,
      -0.005528,
      0.059866,
      -0.074136,
      -0.081454,
      0.040687,
      0.058576,
      0.014216,
      0.016444,
      0.041943,
      -0.006339,
      -0.01542,
      0.074517,
      0.083822,
      0.004434,
      -0.05838,
      0.078675,
      0.066275,
      -0.076093,
      -0.037535,
      -0.013839,
      0.080238,
      0.059765,
      0.085113,
      -0.013523,
      0.044323,
      0.068572,
      -0.034766,
      -0.076311,
      0.002341,
      -0.058418,
      0.078063,
      -0.048513,
      -0.027055,
      -0.061701,
      0.025151,
      0.079205
    ],
    "status": "idea",
    "results": null,
    "repoLink": null,
    "tags": [
      "semantic-drift",
      "temporal-analysis",
      "model-decay",
      "embeddings",
      "research"
    ],
    "createdAt": "2026-03-11T12:00:00Z",
    "updatedAt": "2026-03-11T12:00:00Z"
  }
]